aurh/__init__.py
aurh/__main__.py
aurh-0.0.2.dist-info/LICENSE
aurh-0.0.2.dist-info/METADATA
aurh-0.0.2.dist-info/WHEEL
aurh-0.0.2.dist-info/entry_points.txt
aurh-0.0.2.dist-info/top_level.txt
aurh-0.0.2.dist-info/RECORD
